{
  "displayRestTargetHour":true,
  "keybindShowAdditionalInfo":{
    "keyCode":42,
    "isShiftDown":true,
    "isControlDown":false,
    "isAltDown":false
  },
  "mapConfig":{
    "minY":-58,
    "autoMapBounds":true,
    "maxY":37,
    "minX":-29,
    "cellResolution":9,
    "maxX":49
  },
  "useSearchSouls":true,
  "transferItemsByDefault":true,
  "useSearchTypes":true,
  "useInventoryTextButtons":true,
  "version":1.6,
  "autoFilterToTradable":true,
  "showHelpText":true,
  "components":{
    "serviceSpells":true,
    "options":true,
    "dialog":true,
    "mapPlugin":true,
    "contents":true,
    "console":true,
    "barter":true,
    "rest":true,
    "saveLoad":true,
    "spellmaking":true,
    "map":true,
    "magicSelect":true,
    "quantity":true,
    "inventorySelect":true,
    "tooltip":true,
    "magic":true,
    "stat":true,
    "journal":false,
    "training":true,
    "textInput":false,
    "name":true,
    "inventory":true
  },
  "keybindTakeAll":{
    "keyCode":45,
    "isShiftDown":false,
    "isControlDown":false,
    "isAltDown":false
  },
  "previousConsoleEntries":[{
      "lua":false,
      "text":""
    },{
      "lua":false,
      "text":"ori"
    },{
      "lua":false,
      "text":"tcl"
    },{
      "lua":false,
      "text":"tm"
    },{
      "lua":false,
      "text":"tgm"
    },{
      "lua":false,
      "text":"sethealth 0"
    },{
      "lua":false,
      "text":"tgm"
    },{
      "lua":false,
      "text":"coc balmora"
    },{
      "lua":false,
      "text":"ori"
    },{
      "lua":false,
      "text":"journal HH_DisguisedArmor 150"
    },{
      "lua":false,
      "text":"ori"
    }],
  "displayPlayerDialogueChoices":true,
  "keybindMapSwitch":{
    "keyCode":184,
    "isShiftDown":false,
    "isControlDown":false,
    "isAltDown":true
  },
  "changeMapModeOnCellChange":true,
  "displayWeekday":true,
  "autoSelectInput":"Magic",
  "displayRatio":true,
  "maxWait":1,
  "alwaysClearFiltersOnOpen":true,
  "takeFilteredItems":true,
  "useSearchEffects":true,
  "consoleHistoryLimit":10,
  "selectSpellsOnSearch":true,
  "dialogueTopicSeenColor":"journal_finished_quest_color",
  "useSearch":true,
  "dialogueTopicUniqueColor":"link_color"
}